tripit_utils/__init__.py
tripit_utils/foo.py
tripit_utils-0.0.20230103131342.dist-info/METADATA
tripit_utils-0.0.20230103131342.dist-info/WHEEL
tripit_utils-0.0.20230103131342.dist-info/top_level.txt
tripit_utils-0.0.20230103131342.dist-info/RECORD
