Metadata-Version: 2.1
Name: tripit-utils
Version: 0.0.20230103131342
Summary: Shared libs for tripit projects
Author-email: platform@tripit.com
Classifier: Topic :: Software Development
Requires-Python: >=3.11
